i_xero2/__init__.py
i_xero2/i_flask.py
i_xero2/i_xero.py
i_xero2/i_xero_ui.py
i_xero2-2.13.0.dist-info/METADATA
i_xero2-2.13.0.dist-info/WHEEL
i_xero2-2.13.0.dist-info/licenses/LICENSE
i_xero2-2.13.0.dist-info/RECORD
