Metadata-Version: 2.4
Name: i-xero2
Version: 2.13.0
Summary: Custom connector to Xero
License: MIT
License-File: LICENSE
Keywords: python,xero
Author: Jason Romano
Author-email: aracnid@gmail.com
Requires-Python: >=3.10,<4.0
Classifier: License :: OSI Approved :: MIT License
Classifier: Programming Language :: Python :: 3
Classifier: Programming Language :: Python :: 3.10
Classifier: Programming Language :: Python :: 3.11
Classifier: Programming Language :: Python :: 3.12
Classifier: Programming Language :: Python :: 3.13
Classifier: Programming Language :: Python :: 3.14
Requires-Dist: aracnid-logger (>=1.0,<2.0)
Requires-Dist: flask (>=2.1,<3.0)
Requires-Dist: flask-oauthlib (>=0.9,<0.10)
Requires-Dist: flask-session (>=0.4,<0.5)
Requires-Dist: i-mongodb (>=2.0,<3.0)
Requires-Dist: pytz (>=2022.1,<2023.0)
Requires-Dist: xero-python (>=1.16,<2.0)
Project-URL: Repository, https://github.com/aracnid/i-xero2
